AUTHORS.rst
ChangeLog.rst
LICENSE
MANIFEST.in
README.rst
setup.py
cmsplugin_simple_markdown/__init__.py
cmsplugin_simple_markdown/cms_plugins.py
cmsplugin_simple_markdown/models.py
cmsplugin_simple_markdown/utils.py
cmsplugin_simple_markdown.egg-info/PKG-INFO
cmsplugin_simple_markdown.egg-info/SOURCES.txt
cmsplugin_simple_markdown.egg-info/dependency_links.txt
cmsplugin_simple_markdown.egg-info/requires.txt
cmsplugin_simple_markdown.egg-info/top_level.txt
cmsplugin_simple_markdown/migrations/0001_initial.py
cmsplugin_simple_markdown/migrations/0002_auto__add_field_simplemarkdownplugin_template.py
cmsplugin_simple_markdown/migrations/__init__.py
cmsplugin_simple_markdown/migrations_django/0001_initial.py
cmsplugin_simple_markdown/migrations_django/0002_auto_20160417_1727.py
cmsplugin_simple_markdown/migrations_django/__init__.py
cmsplugin_simple_markdown/templates/cmsplugin_simple_markdown/simple_markdown.html