Metadata-Version: 1.1
Name: cmsplugin-simple-markdown
Version: 1.6
Summary: A plugin for django-cms that provides just a markdown plugin and nothing more.
Home-page: https://www.github.com/Alir3z4/cmsplugin-simple-markdown
Author: Alireza Savand
Author-email: alireza.savand@gmail.com
License: Copyright (c) 2011, Alireza Savand
